cli/__init__.py
cli/cli.py
helpers/__init__.py
helpers/code_builder.py
helpers/nexus_publisher.py
helpers/schema_registry_client.py
helpers/wheel_builder.py
settings/__init__.py
datacontract_helper-0.1.58.dist-info/METADATA
datacontract_helper-0.1.58.dist-info/WHEEL
datacontract_helper-0.1.58.dist-info/entry_points.txt
datacontract_helper-0.1.58.dist-info/top_level.txt
datacontract_helper-0.1.58.dist-info/RECORD
